dataultra.commandlines-0.1.dist-info/WHEEL
dataultra.commandlines-0.1.dist-info/RECORD
dataultra.commandlines-0.1.dist-info/top_level.txt
dataultra.commandlines-0.1.dist-info/METADATA
dataultra.commandlines-0.1.dist-info/zip-safe
dataultra.commandlines-0.1.dist-info/DESCRIPTION.rst
dataultra.commandlines-0.1.dist-info/entry_points.txt
dataultra.commandlines-0.1.dist-info/metadata.json
model/__init__.py
model/undeploycommands.py
model/statiscommands.py
model/stopcommands.py
model/lscommands.py
model/client.py
model/shell.py
model/removecommands.py
model/deletecommands.py
model/deploycommands.py
model/startcommands.py
model/addcommands.py
model/v3_0/__init__.py
model/v3_0/commonnode.py
model/v3_0/application.py
model/v3_0/task.py
model/v3_0/service.py
model/v3_0/cluster.py
model/v3_0/httpclient.py
model/v3_0/instance.py
model/v3_0/microservice.py
model/utils/__init__.py
model/utils/wsclient_utils.py
model/utils/parse_utils.py
model/utils/common_utils.py
model/utils/https_utils.py
model/utils/websocket_utils.py
model/utils/http_utils.py
